simply_notes/__init__.py
simply_notes/main.py
simply_notes-0.1.0.dist-info/METADATA
simply_notes-0.1.0.dist-info/WHEEL
simply_notes-0.1.0.dist-info/entry_points.txt
simply_notes-0.1.0.dist-info/RECORD
